aurblobs/__init__.py
aurblobs/__main__.py
aurblobs/cli.py
aurblobs/constants.py
aurblobs/container.py
aurblobs/errors.py
aurblobs/package.py
aurblobs/repository.py
aurblobs/docker/Dockerfile
aurblobs/docker/build.sh
aurblobs/docker/init.sh
aurblobs/docker/remove.sh
aurblobs/docker/sign.sh
aurblobs/docker/sudoers
aurblobs-0.5.2.dist-info/METADATA
aurblobs-0.5.2.dist-info/RECORD
aurblobs-0.5.2.dist-info/WHEEL
aurblobs-0.5.2.dist-info/entry_points.txt
aurblobs-0.5.2.dist-info/top_level.txt
