Metadata-Version: 2.1
Name: aurblobs
Version: 0.5.2
Summary: Automatically build AUR packages and serve them from a repository
Home-page: https://www.github.com/aurblobs/aurblobs
Author: Martin Weinelt
Author-email: martin+aurblobs@linuxlounge.net
License: AGPL
Platform: UNKNOWN
Requires-Dist: click
Requires-Dist: docker (>=3.0.0)
Requires-Dist: GitPython
Requires-Dist: pretty-bad-protocol (>=3.1.1)
Requires-Dist: requests
Requires-Dist: pyxdg
